LICENSE
MANIFEST.in
README.md
setup.cfg
setup.py
nsaphx/__init__.py
nsaphx/data_node.py
nsaphx/database.py
nsaphx/index.py
nsaphx/log.py
nsaphx/plugin_registery.py
nsaphx/project.py
nsaphx/project_controller.py
nsaphx/registery.py
nsaphx.egg-info/PKG-INFO
nsaphx.egg-info/SOURCES.txt
nsaphx.egg-info/dependency_links.txt
nsaphx.egg-info/top_level.txt
nsaphx/base/__init__.py
nsaphx/base/discovery.py
nsaphx/base/utils.py
nsaphx/plugins/__init__.py
nsaphx/plugins/base.py
nsaphx/plugins/filter/__init__.py
nsaphx/plugins/filter/filter.py