Metadata-Version: 2.1
Name: nsaphx
Version: 0.0.1
Summary: nsaphx is a Python package for causal inference studies using the potential outcome framework. It offers a flexible and extensible framework to apply computational instructions to input data, including exposure, outcome, and confounders. The package uses directed acyclic graphs and database storage for efficient computation and storage.
Home-page: https://github.com/NSAPH-Software/nsaphx
Author: Naeem Khoshnevis
Author-email: nkhoshnevis@g.harvard.edu
Maintainer: Naeem Khoshnevis
Maintainer-email: nkhoshnevis@g.harvard.edu
License: MIT
Classifier: Development Status :: 2 - Pre-Alpha
Classifier: Intended Audience :: Science/Research
Classifier: License :: OSI Approved :: MIT License
Classifier: Natural Language :: English
Classifier: Operating System :: OS Independent
Classifier: Programming Language :: Python :: 3 :: Only
Classifier: Programming Language :: Python :: 3.7
Classifier: Programming Language :: Python :: 3.8
Classifier: Programming Language :: Python :: 3.9
Classifier: Programming Language :: Python :: 3.10
Classifier: Programming Language :: Python :: Implementation :: CPython
Classifier: Programming Language :: Python :: Implementation :: PyPy
Requires-Python: >=3.7
License-File: LICENSE
